Metadata-Version: 2.1
Name: akaocr
Version: 2.1.6
Summary: akaOCR Package Tools
Home-page: UNKNOWN
Author: LauNT
Author-email: ttruongllau@gmail.com
License: Apache License 2.0
Platform: UNKNOWN
Requires-Python: >=3.7
License-File: LICENSE
Requires-Dist: Pillow
Requires-Dist: numpy
Requires-Dist: onnxruntime
Requires-Dist: onnxruntime-gpu
Requires-Dist: opencv-python
Requires-Dist: pyclipper
Requires-Dist: shapely
Requires-Dist: six
